arithmos/__init__.py
arithmos/chain.py
arithmos/cli.py
arithmos/decrypt.py
arithmos/dictionary.py
arithmos/encrypt.py
arithmos/errors.py
arithmos_cipher-4.5.dist-info/LICENSE
arithmos_cipher-4.5.dist-info/METADATA
arithmos_cipher-4.5.dist-info/WHEEL
arithmos_cipher-4.5.dist-info/entry_points.txt
arithmos_cipher-4.5.dist-info/top_level.txt
arithmos_cipher-4.5.dist-info/RECORD
