Metadata-Version: 2.1
Name: arithmos-cipher
Version: 4.5
Summary: A simple Cipher encryption using number
Home-page: https://github.com/LyQuid12/arithmos-cipher
Author: LyQuid
Author-email: lyquidpersonal@gmail.com
License: Apache License 2.0
Project-URL: Source Code, https://github.com/LyQuid12/arithmos-cipher
Project-URL: Discord, https://discord.gg/qpT2AeYZRN
Project-URL: Issue tracker, https://github.com/LyQuid12/arithmos-cipher/issues
Keywords: python,cipher,simple cipher,arithmos,arithmos cipher
Platform: UNKNOWN
Classifier: Development Status :: 5 - Production/Stable
Classifier: Intended Audience :: Science/Research
Classifier: Programming Language :: Python :: 3.7
Classifier: Programming Language :: Python :: 3.8
Classifier: Programming Language :: Python :: 3.9
Classifier: Programming Language :: Python :: 3.10
Classifier: License :: OSI Approved :: Apache Software License
Classifier: Operating System :: Microsoft :: Windows
Classifier: Operating System :: MacOS
Classifier: Operating System :: POSIX :: Linux
Classifier: Operating System :: Android
License-File: LICENSE
Requires-Dist: click
Requires-Dist: requests
Requires-Dist: colorgb
